{
  "tags": [
    "ENV-DESKTOP-gnome",
    "ENV-INSTLANG-en_US",
    "GNOME",
    "generic-desktop",
    "desktop-at-first-boot",
    "test-consoletest_finish-1"
  ],
  "properties": [],
  "area": [
    {
      "width": 65,
      "type": "match",
      "ypos": 10,
      "height": 183,
      "xpos": 54
    },
    {
      "xpos": 6,
      "ypos": 746,
      "height": 20,
      "type": "match",
      "width": 173
    },
    {
      "ypos": 48,
      "height": 78,
      "xpos": 843,
      "type": "match",
      "width": 148
    }
  ]
}